pp_console/__init__.py
pp_console-4.4.55.dist-info/METADATA
pp_console-4.4.55.dist-info/WHEEL
pp_console-4.4.55.dist-info/entry_points.txt
pp_console-4.4.55.dist-info/RECORD
